LICENSE
README.md
setup.cfg
setup.py
poepp/__init__.py
poepp.egg-info/PKG-INFO
poepp.egg-info/SOURCES.txt
poepp.egg-info/dependency_links.txt
poepp.egg-info/requires.txt
poepp.egg-info/top_level.txt
poepp/data_processing/__init__.py
poepp/data_processing/data_dump.py
poepp/data_processing/dump_processing.py
tests/__init__.py
tests/conftest.py
tests/test_dump_processing.py