Metadata-Version: 2.1
Name: poepp
Version: 0.1.2
Summary: A Python package for predicting currency prices in the game Path of Exile
Home-page: UNKNOWN
Author: Kyle Harrison
Author-email: kyleharrison94@hotmail.com
License: LICENSE.md
Platform: UNKNOWN
Provides-Extra: dev
License-File: LICENSE
